trial2vec/__init__.py
trial2vec/base.py
trial2vec/check.py
trial2vec/data.py
trial2vec/demo_data.py
trial2vec/losses.py
trial2vec/metrics.py
trial2vec/model.py
trial2vec/parallel.py
trial2vec/trainer.py
Trial2Vec-0.1.0.dist-info/LICENSE
Trial2Vec-0.1.0.dist-info/METADATA
Trial2Vec-0.1.0.dist-info/WHEEL
Trial2Vec-0.1.0.dist-info/top_level.txt
Trial2Vec-0.1.0.dist-info/RECORD
