Metadata-Version: 2.1
Name: Trial2Vec
Version: 0.1.0
Summary: Pretrained BERT models for encoding clinical trial documents to compact embeddings.
Home-page: https://github.com/RyanWangZf/Trial2Vec
Author: Zifeng Wang
Author-email: zifengw2@illinois.edu
Keywords: clinical trial,machine learning,data mining,information retrieval
Classifier: Programming Language :: Python :: 3
Classifier: Programming Language :: Python :: 3.7
Classifier: Programming Language :: Python :: 3.8
Classifier: Programming Language :: Python :: 3.9
Classifier: License :: OSI Approved :: BSD License
Classifier: Operating System :: OS Independent
License-File: LICENSE
Requires-Dist: datasets
Requires-Dist: joblib
Requires-Dist: nltk
Requires-Dist: numpy
Requires-Dist: pandas
Requires-Dist: textaugment
Requires-Dist: tqdm
Requires-Dist: transformers
Requires-Dist: wget
Requires-Dist: openpyxl
